ErshisiXiaoshiWanzhuanBiteBiQianbaoKaifa/README.md
ErshisiXiaoshiWanzhuanBiteBiQianbaoKaifa/__init__.py
ErshisiXiaoshiWanzhuanBiteBiQianbaoKaifa/__main__.py
ErshisiXiaoshiWanzhuanBiteBiQianbaoKaifa/file.epub
ErshisiXiaoshiWanzhuanBiteBiQianbaoKaifa/index.html
ErshisiXiaoshiWanzhuanBiteBiQianbaoKaifa/css/__init__.py
ErshisiXiaoshiWanzhuanBiteBiQianbaoKaifa/css/annotations.css
ErshisiXiaoshiWanzhuanBiteBiQianbaoKaifa/css/main.css
ErshisiXiaoshiWanzhuanBiteBiQianbaoKaifa/css/normalize.css
ErshisiXiaoshiWanzhuanBiteBiQianbaoKaifa/css/popup.css
ErshisiXiaoshiWanzhuanBiteBiQianbaoKaifa/font/__init__.py
ErshisiXiaoshiWanzhuanBiteBiQianbaoKaifa/font/fontello.eot
ErshisiXiaoshiWanzhuanBiteBiQianbaoKaifa/font/fontello.svg
ErshisiXiaoshiWanzhuanBiteBiQianbaoKaifa/font/fontello.ttf
ErshisiXiaoshiWanzhuanBiteBiQianbaoKaifa/font/fontello.woff
ErshisiXiaoshiWanzhuanBiteBiQianbaoKaifa/img/__init__.py
ErshisiXiaoshiWanzhuanBiteBiQianbaoKaifa/img/annotator-glyph-sprite.png
ErshisiXiaoshiWanzhuanBiteBiQianbaoKaifa/img/annotator-icon-sprite.png
ErshisiXiaoshiWanzhuanBiteBiQianbaoKaifa/img/apple-touch-icon.png
ErshisiXiaoshiWanzhuanBiteBiQianbaoKaifa/img/cancelfullscreen.png
ErshisiXiaoshiWanzhuanBiteBiQianbaoKaifa/img/close.png
ErshisiXiaoshiWanzhuanBiteBiQianbaoKaifa/img/fullscreen.png
ErshisiXiaoshiWanzhuanBiteBiQianbaoKaifa/img/loader.gif
ErshisiXiaoshiWanzhuanBiteBiQianbaoKaifa/img/menu-icon.png
ErshisiXiaoshiWanzhuanBiteBiQianbaoKaifa/img/save.png
ErshisiXiaoshiWanzhuanBiteBiQianbaoKaifa/img/saved.png
ErshisiXiaoshiWanzhuanBiteBiQianbaoKaifa/img/settings-s.png
ErshisiXiaoshiWanzhuanBiteBiQianbaoKaifa/img/settings.png
ErshisiXiaoshiWanzhuanBiteBiQianbaoKaifa/img/star.png
ErshisiXiaoshiWanzhuanBiteBiQianbaoKaifa/js/__init__.py
ErshisiXiaoshiWanzhuanBiteBiQianbaoKaifa/js/epub.js
ErshisiXiaoshiWanzhuanBiteBiQianbaoKaifa/js/epub.min.js
ErshisiXiaoshiWanzhuanBiteBiQianbaoKaifa/js/epub.min.map
ErshisiXiaoshiWanzhuanBiteBiQianbaoKaifa/js/hooks.min.js
ershisi_xiaoshi_wanzhuan_bite_bi_qianbao_kaifa-2024.3.4.0.dist-info/METADATA
ershisi_xiaoshi_wanzhuan_bite_bi_qianbao_kaifa-2024.3.4.0.dist-info/WHEEL
ershisi_xiaoshi_wanzhuan_bite_bi_qianbao_kaifa-2024.3.4.0.dist-info/entry_points.txt
ershisi_xiaoshi_wanzhuan_bite_bi_qianbao_kaifa-2024.3.4.0.dist-info/top_level.txt
ershisi_xiaoshi_wanzhuan_bite_bi_qianbao_kaifa-2024.3.4.0.dist-info/RECORD
